crop_yolo/__init__.py
crop_yolo/main.py
crop_yolo-1.1.0.dist-info/METADATA
crop_yolo-1.1.0.dist-info/WHEEL
crop_yolo-1.1.0.dist-info/entry_points.txt
crop_yolo-1.1.0.dist-info/top_level.txt
crop_yolo-1.1.0.dist-info/RECORD
