Metadata-Version: 2.1
Name: crop-yolo
Version: 1.1.0
Summary: Crop people from jpg files via yolo v10
Author-email: tadeasf <business@tadeasfort.com>
Classifier: Development Status :: 3 - Alpha
Classifier: Intended Audience :: Developers
Classifier: License :: OSI Approved :: MIT License
Classifier: Programming Language :: Python :: 3
Requires-Python: >=3.12
Requires-Dist: build >=1.2.2
Requires-Dist: certifi >=2024.8.30
Requires-Dist: charset-normalizer >=3.3.2
Requires-Dist: click >=8.1.7
Requires-Dist: contourpy >=1.3.0
Requires-Dist: cycler >=0.12.1
Requires-Dist: filelock >=3.16.0
Requires-Dist: fonttools >=4.53.1
Requires-Dist: fsspec >=2024.9.0
Requires-Dist: idna >=3.10
Requires-Dist: jinja2 >=3.1.4
Requires-Dist: kiwisolver >=1.4.7
Requires-Dist: markdown-it-py >=3.0.0
Requires-Dist: markupsafe >=2.1.5
Requires-Dist: matplotlib >=3.9.2
Requires-Dist: mdurl >=0.1.2
Requires-Dist: mpmath >=1.3.0
Requires-Dist: networkx >=3.3
Requires-Dist: opencv-python >=4.10.0.84
Requires-Dist: packaging >=24.1
Requires-Dist: pandas >=2.2.2
Requires-Dist: pillow >=10.4.0
Requires-Dist: pip-tools >=7.4.1
Requires-Dist: psutil >=6.0.0
Requires-Dist: py-cpuinfo >=9.0.0
Requires-Dist: pygments >=2.18.0
Requires-Dist: pyparsing >=3.1.4
Requires-Dist: pyproject-hooks >=1.1.0
Requires-Dist: python-dateutil >=2.9.0.post0
Requires-Dist: pytz >=2024.2
Requires-Dist: pyyaml >=6.0.2
Requires-Dist: requests >=2.32.3
Requires-Dist: rich >=13.8.1
Requires-Dist: scipy >=1.14.1
Requires-Dist: seaborn >=0.13.2
Requires-Dist: shellingham >=1.5.4
Requires-Dist: six >=1.16.0
Requires-Dist: sympy >=1.13.2
Requires-Dist: torch >=2.4.1
Requires-Dist: torchvision >=0.19.1
Requires-Dist: tqdm >=4.66.5
Requires-Dist: typer >=0.12.5
Requires-Dist: typing-extensions >=4.12.2
Requires-Dist: tzdata >=2024.1
Requires-Dist: urllib3 >=2.2.3
Requires-Dist: wheel >=0.44.0
Requires-Dist: ultralytics >=8.2.94
Requires-Dist: numpy >=1.26.4
Requires-Dist: ultralytics-thop >=2.0.6
